_pafprocess.cpython-37m-darwin.so
tf_pose/__init__.py
tf_pose/common.py
tf_pose/datum_pb2.py
tf_pose/estimator.py
tf_pose/eval.py
tf_pose/network_base.py
tf_pose/network_cmu.py
tf_pose/network_dsconv.py
tf_pose/network_mobilenet.py
tf_pose/network_mobilenet_thin.py
tf_pose/network_mobilenet_v2.py
tf_pose/networks.py
tf_pose/pose_augment.py
tf_pose/pose_dataset.py
tf_pose/pystopwatch.py
tf_pose/runner.py
tf_pose/train.py
tf_pose/mobilenet/__init__.py
tf_pose/mobilenet/conv_blocks.py
tf_pose/mobilenet/mobilenet.py
tf_pose/mobilenet/mobilenet_v2.py
tf_pose/pafprocess/__init__.py
tf_pose/pafprocess/numpy.i
tf_pose/pafprocess/pafprocess.h
tf_pose/pafprocess/pafprocess.i
tf_pose/pafprocess/pafprocess.py
tf_pose/pafprocess/setup.py
tf_pose/slidingwindow/ArrayUtils.py
tf_pose/slidingwindow/Batching.py
tf_pose/slidingwindow/Merging.py
tf_pose/slidingwindow/RectangleUtils.py
tf_pose/slidingwindow/SlidingWindow.py
tf_pose/slidingwindow/WindowDistance.py
tf_pose/slidingwindow/__init__.py
tf_pose/tensblur/__init__.py
tf_pose/tensblur/smoother.py
tf_pose_data/__init__.py
tf_pose_data/graph/cmu/download.sh
tf_pose_data/graph/mobilenet_thin/graph_opt.pb
tf_pose-0.11.0.dist-info/LICENSE
tf_pose-0.11.0.dist-info/METADATA
tf_pose-0.11.0.dist-info/WHEEL
tf_pose-0.11.0.dist-info/dependency_links.txt
tf_pose-0.11.0.dist-info/top_level.txt
tf_pose-0.11.0.dist-info/RECORD
